{
  "date": "1993년 4월 18일",
  "author": null,
  "content": "p.5 내가 처음 뵌 첫 선배님? 잔소리하고 뭐 떨어졌다네+. 자신 없음기면 아픈 곡 읽는.\n\n요는 93. 4.18 구중 대장전에 갔다. (p.5 도지는 앞녀, 도호대) 앉혀이 깨졌음). 나중은 사랑이다. 그러나 갔다.\n남은 외싸하며 사논 내 허였심이 나를 괴게 하깥까,\n아니였 진정으로 고정함녀 이땅의 특사이기 때문에!\n간절까. 아우레도 뜰다. 지는 배가 너욱 북로다.\n브랜 완에 이완결에 과니 상정념을 완/웃어서 그런 카 보다.\n뻐, 골강 거짓사로 카지 앏고, 여기에 들은 쩌 잘까?\n아깟도 [불명확] 낭아셔 믹까 낭들과) 떨려지오 물화하는\n깜려기? (우뒤레씨) 안짤됨이 깜림요뭇서 찰 단감웨었 다\n여거가 아디즐 인지? 10씨 까셔 롤려보, 또 10씨 가서\n롤려고, 그렇다카 우싶먼에 조직하충 6대 잠 기떳다.\n마지, 취까 뺘롤에) 빼걸나다 하싶을 보는곤 깜왈다.\n비족 카 들려네, 지하로 내려까져 채씬음 돌보는데/\n바) 래씬음 북다그 그랬지. (??). 다증족 서핸지자이다.\n갈 바다 깜다. 공난은 언제하고? 하니, 사방꾼이나\n여여아겠다. 그 사방 왔고 긑 웬 데아지. 단죽은 궤로\n밣겼다. peper 은 아저써가 궁짐다. 노침성임런다.\n아깟이 서울 방숙씩 신(easy of castle (confidence 라고\n어였까? 비비면, post-modernism 이렇고\n마우해은 츠다.\n1993.4.18 왔, 겨숨,\n\n[하단 파란색 필기]\n어제 쎄벙씨에 앗갔다. 괜안족 비웃면 뽀온 이짜게 깎자짝\n짜있면 나은 자앗은 았다. 처자 신싼바띠 지써\n뿐 왔다 께껐다. 자나 3.4월음을 되찬한 현면 새헛자도\n저리쨌 어햍게 뭣켱다. 저상 내다. 배껴하 깡삼은 신깜",
  "summary": "1993년 4월 18일 구중 대장전에 간 경험과 그 과정에서의 감정, 고민들을 중심으로 쓴 일상 기록. 신앙적 고민과 인간관계에 대한 성찰이 담겨 있음.",
  "tags": [
    "일상",
    "고민",
    "신앙",
    "대학생활",
    "감정기록"
  ],
  "mood": "neutral",
  "decade": "1990s",
  "image_quality": "fair",
  "filename": "1993년_열린마음_p073.jpg",
  "processed_at": "2026-04-09T18:23:31.242396",
  "volume_id": "1993년_열린마음",
  "volume_title": "1993년 열린마음",
  "year": 1993,
  "page_label": "p073"
}