{
  "date": null,
  "author": null,
  "content": "명랑하 깊새움\n\n내가어떤- 중년센 시대 못했겠다.\n나 없어 곤충에 여죽어는 사람이나/나 하태면 바꿔라.\n며칠 중 있이 싯겠다. 그 첫장집는 몸 나뀌킨다.\n앗다다 6시간 나에게 히찬 있마를 솜가?\n'팜 이 미움이 빠뭄다. 잔턱 내 삶테는 삶움다.\n내가 처는 인본는네 경혼 바런송어시 곡는 깐이 아니음 굼아나봤다.\n\n——짱네! ——\n\n[스케치: 연결된 말풍선 3개 그림]\n\n[원 안의 스케치]\n\n음음고 여중 되어 음 삶서 깨엔을 빠서 앗은 비음 다른 되\n까선서 파멸어는 깊이 됨짜다. [불명확] 새벨 네 식 뭔, 하던어는\n불과 쏟, 가럼, 다... 이 하나 모테사 더 이해 잦은 쏘는 이이이다\n해본에서, 노중 됨어, 깨어 [불명확] 깨이어 여팀에 버번과 대해.\n놈이 각는 생의 여여 쎘습, 꼻이, 나침. 처염서 깨다서 이이나\n시중 @@는 벼라. 깨내 나겨어 괴뭐는 긱설, 거세이 벼사서 (닫과?)\n깨단 이이나 대함서 톤이... 더 이해 깨뭉 깨텨러 좋 꽃치.\n뽀 더 자서 느즕 봇이 똑숀나. 뫼 꼬라는 톱받다 이이 like 돌에요.\n자므이 깏는 ###에 처서 나공자 촉실, 긱슨, 스욕주어 깨든 또껜\n많은 짝켜나 긋연 께왓나다.\n버이 고깨 깨켜여. 동내는, 자서 곳없이 M.T로 다칠시켜 깊는 —>를 젛해",
  "summary": "개인적인 고민과 감정을 표현한 일상 노트. 삶의 의미와 관계에 대한 깊이 있는 생각을 담고 있으며, 중간에 말풍선 스케치가 있다.",
  "tags": [
    "일상",
    "고민",
    "감정",
    "철학적사유"
  ],
  "mood": "neutral",
  "decade": "1990s",
  "image_quality": "fair",
  "filename": "1993년_열린마음_p009.jpg",
  "processed_at": "2026-04-09T18:09:24.419519",
  "volume_id": "1993년_열린마음",
  "volume_title": "1993년 열린마음",
  "year": 1993,
  "page_label": "p009"
}