{
  "date": "1999-04-01",
  "author": null,
  "content": "엊날 냥이 도꺼?\n도마 Ghost 야셔 깨달은 쉬레기가 - 숨어있던 죄심이와 울다 못함\n도아가 앞을 떼며 냥자 빠졌찌까?\n\n어 못한 나 이게 씨크한 깡돌씽메 너곡 안댓이 내까요어하다.\n참지만 내새기 한국 저씩이가 왔다. 여족 좋진자 조광에서 악자의 우려가 지겨다 이렇저했다. 나아까 냥에서 밤처는 차차 뭉꼬이 뽑뭉은 짜았다 맞은이 발젓은데 [불명확] 뭉국 칠젓 시간에 옛은이 정원 떠떠 [불명확] 간단. 네까 내 성격은 비음에 같은 O[?]. 나아까 냥에서 밤처는 렷없는 임국이 되겠여 임다. 지금의 땅곰 나 내정성다 어의지 마 [불명확] CI포은의 내여국은 내 씨어의 것다. 내가 내 O국은 칠장정 ̲̲̲̲. 육국의 나의 문능은 씨해 싶다지 상구은 하고 맺습다 꼳다.\n\n명지가 이렇던 성감이 미타하였든 [불명확]국 밤다.\n\n- 씨에 [불명확] 미더은 마적로 도아을 O/나[?] -\n\nP.S. - 나분 톡딴하게 숨기쌌다. 성감은 곧은더 왜 칠신가 않되지?\n\n사와톡 이여 내 것어절 토톡 비미 욕 외해 샘지 더새 [불명확]\n정작에 제었싹을 상저 여자로 미자있을 상지 미저은.\n사와톡 이여 내 것어절 토톡 욕없 욕 외해 밤묻지 여절은\n자다자 내미야싹을 상저 미자은 미저을 여절은\n뭉 상곰 지다 외혜이 이여 쌍을 자자은\n꼬더겸 나성 항이은 감싸싸 환곰 앎으은 앎요 앎은\n기 최곡은 미묻 하떠 꼬싸 뭐이겨싸 나벗 어청 본 쪽\n욕여은 욕여은 욕여을.\n\n- 나삭 여싹에 대해 잠깐 자지란 상정 -\n1990 4. 1   [?]",
  "summary": "작성자가 복잡한 감정과 고민을 표현하는 개인적인 일기 형식의 글. 관계나 성격에 대한 자아성찰과 고뇌가 담겨있으며, 마지막에 반복되는 문장들로 혼란스러운 심리 상태를 드러냄.",
  "tags": [
    "고민",
    "자아성찰",
    "일상",
    "감정"
  ],
  "mood": "negative",
  "decade": "1990s",
  "image_quality": "fair",
  "filename": "1993년_열린마음_p032.jpg",
  "processed_at": "2026-04-09T18:14:43.820296",
  "volume_id": "1993년_열린마음",
  "volume_title": "1993년 열린마음",
  "year": 1993,
  "page_label": "p032"
}