{
  "date": "1995-12-16",
  "author": null,
  "content": "아침마다 하는 것만\n아침마다 하지 않습니다\n그래서 비효은 하지 않습니다.\n\n'92년도, 용담 은혜 서금 쌓는 순간과의 것 이런껑 ㅂ됨 고마쇼!\n\n-주댓 / 어머나!! 웬! 아나!!\n\n자는 in 윤이라고 모아야(?)이다 보는중\n떨어 있었던 모한데\n\n<<서쪽 다 읽는 사람은 뭐시려고>> 뭐. 공 근은 쯤은에 있고.\n(이) 서물에 관한다.\n\n내 곳들중의 이렇게 향하는, 하니짝, However, 1960, 아직도\nReport과 1070쳐서, term paper도 많 때양났.\n96년을 어정져 몇 않은겠고는.\n반더, 서도의 다 맞춘의 왔?\n\n자손후술수지, 다짜 공아지고, 버불났던 윤더지.\n\n진너가 곡살자, 작엔 요저정비었다.\n\n곡서나 뭔강'이랑, 늘 아렇 살아였다 곡싱지가 명 살싸여 [불명확] 과더시도.\n받아였던 뭔강' 이떴옹 것.\n\n곡려서, 은매 '96이 요았던지 자면었다. 이것을 봐야'겨도 았끝여\n들정지?\n\n95. 12. 16. 정식.",
  "summary": "1995년 12월 16일 작성된 일상 노트로, 아침 일과와 학업 관련 고민, 그리고 1996년을 앞두고 있는 반성과 계획에 대해 기록하고 있습니다.",
  "tags": [
    "일상",
    "고민",
    "학업",
    "새해계획",
    "1990년대"
  ],
  "mood": "neutral",
  "decade": "1990s",
  "image_quality": "fair",
  "filename": "1995년_열린마음_p049.jpg",
  "processed_at": "2026-04-09T18:41:43.301802",
  "volume_id": "1995년_열린마음",
  "volume_title": "1995년 열린마음",
  "year": 1995,
  "page_label": "p049"
}