{
  "date": null,
  "author": null,
  "content": "[불명확한 필기로 인해 정확한 전사 어려움] 대부분의 텍스트가 작은 필기체로 여러 겹으로 쓰여있어 개별 문장 판독 곤란. 간단한 단어들과 기호(화살표, 원형 표시 등)가 산재되어 있으나 전체 맥락 파악 불가",
  "summary": "여러 겹의 작은 필기로 채워진 노트 페이지. 정확한 내용 판독이 매우 어려움.",
  "tags": [
    "일상",
    "노트"
  ],
  "mood": "neutral",
  "decade": "1990s",
  "image_quality": "poor",
  "filename": "1996년_1번째_이심이_p028.jpg",
  "processed_at": "2026-04-09T23:04:37.664755",
  "volume_id": "1996년_1번째_이심이",
  "volume_title": "1996년 1번째 이심이",
  "year": 1996,
  "page_label": "p028"
}