{
  "date": null,
  "author": null,
  "content": "행복 Be-cause you are.\n\n너의 행복이 나의 행복이고 나의 행복이 너의 행복이었으면 좋겠어. 그리고 우리 모두 행복했으면 좋겠어. 인생이란 여행지 같아서 언제나 새로운 풍경이 기다리고 있어. 그것도 좋은 것만 있으면 좋겠는데 세상은 그렇게 만들어지지 않았나봐.\n\n그래도 우리는 계속 앞으로 나아가야 해. 왜냐하면 멈추면 더 이상 앞으로 나아갈 수 없으니까.\n\n[불명확] 내가 [불명확] 수 있는 방법은 뭘까?\n\n아무튼 다들 화이팅하고 앞으로 나아가자!\n\nP.S 우리 모두 행복하자!! 열심히 공부해서 그 이상의 [불명확]\n\n행운을 빈다 580 6396",
  "summary": "행복에 대한 철학적 성찰과 함께 모두가 함께 행복해지기를 바라는 마음을 담은 글. 인생의 여정 속에서 계속 앞으로 나아가야 함을 강조하고 격려의 메시지를 전함.",
  "tags": [
    "일상",
    "행복",
    "격려",
    "철학"
  ],
  "mood": "positive",
  "decade": "1990s",
  "image_quality": "fair",
  "filename": "1999년_열린마음_p010.jpg",
  "processed_at": "2026-04-09T23:21:31.149177",
  "volume_id": "1999년_열린마음",
  "volume_title": "1999년 열린마음",
  "year": 1999,
  "page_label": "p010"
}