{
  "date": null,
  "author": "Kinney",
  "content": "사람이 다 미쳐갈 놈다 그렇게 심심한가\n여기 이상하고 사서 무르이고 좋나 마주 앉도록\n써놓으면은 내똑제 때마 내가다 줄것 눈것이다\n가도 따라 버갔다다들 Kinney\n\n[불명확] 댓글졸졸\n\n이것 [불명확] 지겨다\n뭔 기나죽에다 은닌재 [불명확]다\n짚음에 지태[불명확]도\n이것 중 지겨운은\n재밌 [불명확] 네 긴[불명확]에 [불명확]이 나버하지 담\n실[불명확](1) 논문마 나버하인...\n\n아...\n다또 아지 앉는가\n짓마하은 나머한이 오네다!\n\nComma짐(1)\n\n원장이 이제 코데 놓게 가지 겠다\n내 열애하면 코더 코훔 끝나고 간다고 골은나가\n코더가민 중은 중 알아다        진정",
  "summary": "일상적인 고민과 스트레스, 답답한 마음을 솔직하게 표현한 노트 페이지. 감정적인 상태가 반영되어 있으며 미래에 대한 불안감이 드러난다.",
  "tags": [
    "일상",
    "고민",
    "감정",
    "스트레스"
  ],
  "mood": "negative",
  "decade": "2000s",
  "image_quality": "fair",
  "filename": "2000년_열린마음_p044.jpg",
  "processed_at": "2026-04-09T23:38:04.364772",
  "volume_id": "2000년_열린마음",
  "volume_title": "2000년 열린마음",
  "year": 2000,
  "page_label": "p044"
}