{
  "date": null,
  "author": "꽃이 (서명)",
  "content": "선뜻 내게 넓게 마음이 돌아온다.\n은중은 것지에서 따라 다우치 수 있다.\n그러고 것지와 하나인 것 야아하지만\n서로존재에서 따른 운곡에 따라 다우치 수 있다.\n무릎 그 다웅이나 바뀌어나 수월가 다우치 수 있다는 말이다.\n\n안돈 나는 것말 그것도 서각했다.\n왈씨 그것 꼬말은 하는 있다.\n=것지만 그 [불명확] 또 이향오야야 화는 것\n네 운곡 서전을 잘 때여하는 것, 초대한 한장게 하는 것은\n위해 깬았어이 나는 다르거는 것이 겠지!\n\n저만 할 수다이다는 느는겠지면\n궤의 마응 저만 '꼬자' 요 한장한 아는 것 같다.\n\n기[불명확]으로 왈씨 마음이 옷은 며는 있다\n그래서 한아낸다.\n\n마는 사랑들에게 왕은 '아존'이다. 문은 등. 나는 나. 제을 웃은 고달은\n하는 기는 운전한 못지. 높여한 좋은 기는 나.\n\n그렀게 배우한는 삶의 갈들에서 즐서짐 중밤적으,\n저시게는 곱게제 때살 서옳에서 기처침 기게 때처즉,\n째 시작 위해로 사터 다른 때은 같이에 교로청 이데중즉.",
  "summary": "작성자가 마음의 변화와 인간관계, 자아실현에 대한 깊이 있는 성찰을 나누고 있습니다. 사랑, 존재, 성장의 의미에 대해 고민하는 내용입니다.",
  "tags": [
    "고민",
    "철학적 사색",
    "성찰",
    "관계",
    "일상"
  ],
  "mood": "neutral",
  "decade": "1990s",
  "image_quality": "fair",
  "filename": "2000년_열린마음_p144.jpg",
  "processed_at": "2026-04-09T23:54:02.064225",
  "volume_id": "2000년_열린마음",
  "volume_title": "2000년 열린마음",
  "year": 2000,
  "page_label": "p144"
}